{"assets/gifs/clear_sky.gif":["assets/gifs/clear_sky.gif"],"assets/gifs/clouds.gif":["assets/gifs/clouds.gif"],"assets/gifs/error.jpeg":["assets/gifs/error.jpeg"],"assets/gifs/rain.gif":["assets/gifs/rain.gif"],"assets/gifs/snow.gif":["assets/gifs/snow.gif"],"assets/gifs/wind.gif":["assets/gifs/wind.gif"],"assets/icons/.DS_Store":["assets/icons/.DS_Store"],"assets/icons/clear.png":["assets/icons/clear.png"],"assets/icons/clouds.png":["assets/icons/clouds.png"],"assets/icons/drizzle.png":["assets/icons/drizzle.png"],"assets/icons/first.gif":["assets/icons/first.gif"],"assets/icons/humidity.png":["assets/icons/humidity.png"],"assets/icons/mist.png":["assets/icons/mist.png"],"assets/icons/rain.png":["assets/icons/rain.png"],"assets/icons/snow.png":["assets/icons/snow.png"],"assets/icons/wind.png":["assets/icons/wind.png"]}